{
  "MutagenObjectType": "ArmorModification",
  "FormKey": "00083F:RBPrideBandanas.esp",
  "VersionControl": 11971,
  "EditorID": "EGBtR_mod_Bandana_Skin_Misc_Stripes",
  "Name": {
    "TargetLanguage": "English",
    "Value": "Striped Design"
  },
  "Description": {
    "TargetLanguage": "English",
    "Value": ""
  },
  "AttachPoint": "000838:RBPrideBandanas.esp",
  "TargetOmodKeywords": [
    "00083A:RBPrideBandanas.esp"
  ],
  "LooseMod": "003F5E:RBPrideBandanas.esp",
  "Properties": [
    {
      "MutagenObjectType": "ObjectModFormLinkIntProperty`1",
      "Property": "Keywords",
      "Record": "00081F:RBPrideBandanas.esp",
      "Value": 441,
      "FunctionType": "Add"
    },
    {
      "MutagenObjectType": "ObjectModFormLinkIntProperty`1",
      "Property": "MaterialSwaps",
      "Record": "17E920:Fallout4.esm",
      "Value": 441,
      "FunctionType": "Add"
    }
  ]
}